pidotlcd/__init__.py
pidotlcd/display.py
pidotlcd/display_driver.py
pidotlcd/font.py
PiDotLCD-0.1.1.dist-info/LICENSE
PiDotLCD-0.1.1.dist-info/METADATA
PiDotLCD-0.1.1.dist-info/WHEEL
PiDotLCD-0.1.1.dist-info/top_level.txt
PiDotLCD-0.1.1.dist-info/RECORD
